<?xml version="1.0" encoding="utf-8"?>

<ArrayOfDouble xmlns:xsi="http://www.w3.org/2001/XMLSchema-instance" xmlns:xsd="http://www.w3.org/2001/XMLSchema">
    <double>2.6546340373919577</double>
    <double>3.0200378551089893</double>
    <double>3.2285146997670275</double>
    <double>3.3823886874382731</double>
    <double>3.5058967004434409</double>
    <double>3.6168662520651558</double>
    <double>3.7136387614080681</double>
    <double>3.8011956947269834</double>
    <double>3.8837465463068881</double>
    <double>3.9573635012155561</double>
    <double>4.027876033589787</double>
    <double>4.09482394544137</double>
    <double>4.1577758102478954</double>
    <double>4.2176250212930357</double>
    <double>4.2752814172833551</double>
    <double>4.331434704081615</double>
    <double>4.386812246483685</double>
    <double>4.4377540742008641</double>
    <double>4.4885467498521194</double>
    <double>4.5378790991784941</double>
    <double>4.5863064750477252</double>
    <double>4.6331263826794675</double>
    <double>4.6792393313949887</double>
    <double>4.7246119316337785</double>
    <double>4.7686873495343631</double>
    <double>4.8113486965289134</double>
    <double>4.8544658682950752</double>
    <double>4.8964418215696632</double>
    <double>4.9377209823819914</double>
    <double>4.97898242167264</double>
    <double>5.0196307356905789</double>
    <double>5.0596772436233</double>
    <double>5.0985499305349551</double>
    <double>5.1364806760482544</double>
    <double>5.1740831110194909</double>
    <double>5.211913738552246</double>
    <double>5.2495396538616541</double>
    <double>5.2857970746068395</double>
    <double>5.3224530207210963</double>
    <double>5.3593466164215071</double>
    <double>5.395352854851744</double>
    <double>5.4309836682350578</double>
    <double>5.4660975698372489</double>
    <double>5.5005245513263272</double>
    <double>5.535434675310535</double>
    <double>5.5694504375949245</double>
    <double>5.60359259723244</double>
    <double>5.6372872749083704</double>
    <double>5.6710625960387961</double>
    <double>5.7054049101617368</double>
    <double>5.7391112345082327</double>
    <double>5.7725094695453691</double>
    <double>5.8063469062876241</double>
    <double>5.8395712199377838</double>
    <double>5.8721248913913051</double>
    <double>5.9049343736990707</double>
    <double>5.9377855258615133</double>
    <double>5.9703971432321277</double>
    <double>6.0028755535060894</double>
    <double>6.0350999612826461</double>
    <double>6.0674826661112782</double>
    <double>6.0996782805116325</double>
    <double>6.1312806139692091</double>
    <double>6.1631597468498631</double>
    <double>6.1953909511100766</double>
    <double>6.2275823825769159</double>
    <double>6.2592951577794169</double>
    <double>6.2910668027495653</double>
    <double>6.3217676280275326</double>
    <double>6.3532163878914654</double>
    <double>6.3857223542197188</double>
    <double>6.4166224253146131</double>
    <double>6.4482837667487107</double>
    <double>6.47926411755875</double>
    <double>6.5097818329733581</double>
    <double>6.5410410138722757</double>
    <double>6.5728497956461887</double>
    <double>6.6043125631835995</double>
    <double>6.6359188169807446</double>
    <double>6.66756080307616</double>
    <double>6.6978904320095562</double>
    <double>6.7303046688593637</double>
    <double>6.7617922928697851</double>
    <double>6.7935446636849326</double>
    <double>6.8252161320473519</double>
    <double>6.8567567074998133</double>
    <double>6.888567926292712</double>
    <double>6.9201530690328745</double>
    <double>6.9523720579541628</double>
    <double>6.9843022281788736</double>
    <double>7.0168858794352094</double>
    <double>7.0484590179411208</double>
    <double>7.0803023392220332</double>
    <double>7.1123150094743668</double>
    <double>7.1452025387573075</double>
    <double>7.1773272878025782</double>
    <double>7.2083727761340661</double>
    <double>7.2397234228423359</double>
    <double>7.2727374956474566</double>
    <double>7.304756914114475</double>
    <double>7.33758527964837</double>
    <double>7.3700314569949557</double>
    <double>7.4028862749231035</double>
    <double>7.4363729077858993</double>
    <double>7.4697267642571425</double>
    <double>7.502417417080232</double>
    <double>7.5356239984511788</double>
    <double>7.5694832668418828</double>
    <double>7.6028584176889868</double>
    <double>7.6369503998673363</double>
    <double>7.6712272541325195</double>
    <double>7.705387287960062</double>
    <double>7.7393201001255649</double>
    <double>7.7737772560074054</double>
    <double>7.808091203023241</double>
    <double>7.8433237805247806</double>
    <double>7.8782493215324889</double>
    <double>7.91386917655142</double>
    <double>7.9496340965571495</double>
    <double>7.9856329166792728</double>
    <double>8.02143245899116</double>
    <double>8.057253956745356</double>
    <double>8.0924627854182454</double>
    <double>8.1286762167728117</double>
    <double>8.1662934612474345</double>
    <double>8.203367766573809</double>
    <double>8.240341737821721</double>
    <double>8.2788345337699241</double>
    <double>8.3174679040502539</double>
    <double>8.3553880934447928</double>
    <double>8.39334453350622</double>
    <double>8.4318054465723815</double>
    <double>8.4702487792537635</double>
    <double>8.5103680982082839</double>
    <double>8.5498190349169</double>
    <double>8.5894141949190956</double>
    <double>8.6307144332390173</double>
    <double>8.6717771205946086</double>
    <double>8.7123047245390133</double>
    <double>8.7536626233108876</double>
    <double>8.7956317705835581</double>
    <double>8.83693178602886</double>
    <double>8.87937702649547</double>
    <double>8.9233321313900138</double>
    <double>8.9674928556026927</double>
    <double>9.01229394050696</double>
    <double>9.0563332097359162</double>
    <double>9.1027474926967535</double>
    <double>9.1482808250770624</double>
    <double>9.19427253852762</double>
    <double>9.2406738305008691</double>
    <double>9.2888198518213763</double>
    <double>9.3375530526477171</double>
    <double>9.3879346467268</double>
    <double>9.43930407697986</double>
    <double>9.4888925621819</double>
    <double>9.5404288728895459</double>
    <double>9.5917367447701345</double>
    <double>9.64555773703637</double>
    <double>9.6999781795683688</double>
    <double>9.75492170631859</double>
    <double>9.8109332257727466</double>
    <double>9.8698054088627281</double>
    <double>9.9286915474693433</double>
    <double>9.9877461160854981</double>
    <double>10.046844864455684</double>
    <double>10.109131821024418</double>
    <double>10.172914081110889</double>
    <double>10.238106887349321</double>
    <double>10.303705859798523</double>
    <double>10.371335369190959</double>
    <double>10.440882390511762</double>
    <double>10.514028046182501</double>
    <double>10.59084637351134</double>
    <double>10.667347935129286</double>
    <double>10.745505875904723</double>
    <double>10.8275754396822</double>
    <double>10.912331033841795</double>
    <double>10.99969530337297</double>
    <double>11.089430256172442</double>
    <double>11.184642582348426</double>
    <double>11.281626977150003</double>
    <double>11.381592381059845</double>
    <double>11.48873242599193</double>
    <double>11.60303558293934</double>
    <double>11.724598582709573</double>
    <double>11.850499004996822</double>
    <double>11.982998615523584</double>
    <double>12.127480186409205</double>
    <double>12.279936940685513</double>
    <double>12.446404377537581</double>
    <double>12.625947598249164</double>
    <double>12.83190682687969</double>
    <double>13.05772524256045</double>
    <double>13.308281872680148</double>
    <double>13.613391862211971</double>
    <double>13.981080687179222</double>
    <double>14.470646805422163</double>
    <double>15.170159379852919</double>
    <double>16.559973833490861</double>
</ArrayOfDouble>